test_20-21/2018A7PS0284P.v
// Egna Praneeth Gummana
// 2018A7PS0284P

module RSff(Q, Qbar, S, R, clk, clear);
	output Q, Qbar;
	input S, R, clk, clear;
	reg Q, Qbar;
	always@(posedge clk)begin
		if(clear) begin
		Q <= 0;
		Qbar <= 1;
		end
		else begin
			case ({S, R})
				2'b01: begin
						Q <= 0;
						Qbar <= 1;
						end
				2'b10: begin 
						Q <= 1;
						Qbar <= 0;
					end
				2'b11:begin 
						Q <= 1;
						Qbar <= 0;
					end
			endcase
		end
		
	end
endmodule

module Dff ( Q, Qbar, D, clk, clear);
	input D, clk, clear;
	output Q, Qbar;
	wire Dnot;
	
	not n1 (Dnot, D);
	RSff r1 (Q, Qbar, D, Dnot, clk, clear);
endmodule

module Ripple_Counter(Q, clk, clear);
	input clear, clk;
	output [3:0] Q;
	wire q0, q1, q2, q3;
	
	Dff d1 (Q[0], q0, q0, clk, clear); 
	Dff d2 (Q[1], q1, q1, q0, clear);
	Dff d3 (Q[2] , q2, q2, q1, clear);
	Dff d4 (Q[3], q3, q3, q2, clear);
	
endmodule


module MEM1(out, Addr);
	input [2:0] Addr;
	output [8:0] out;
	reg [7:0] mem [8:0] ;
	reg [8:0] out;
	
	initial
	begin
	mem[0] = 9'b0001_1111_1;
	mem[1] = 9'b0011_0001_1;
	mem[2] = 9'b0101_0011_1;
	mem[3] = 9'b0111_0101_1;
	mem[4] = 9'b1001_0111_1;
	mem[5] = 9'b1011_1001_1;
	mem[6] = 9'b1101_1011_1;
	mem[7] = 9'b1111_1101_1;
	end
	
	always@(Addr)
	begin
	out = mem[Addr]; 
	end
	
	endmodule
	
module MEM2(out, Addr);
	input [2:0] Addr;
	output [8:0] out;
	reg [7:0] mem [8:0] ;
	reg [8:0] out;
	
	initial
	begin
	mem[0] = 9'b0000_0000_0;
	mem[1] = 9'b0010_0010_0;
	mem[2] = 9'b0100_0100_0;
	mem[3] = 9'b0110_0110_0;
	mem[4] = 9'b1000_1000_0;
	mem[5] = 9'b1010_1010_0;
	mem[6] = 9'b1100_1100_0;
	mem[7] = 9'b1110_1110_0;
	end
	
	always@(Addr)
	begin
	out = mem[Addr]; 
	end
	
	endmodule



module MUX2To1(out, in1, in2, sel);
	output out;
	input in1, in2, sel;
	assign out = sel ? in2 : in1;
endmodule

module MUX16to8( out, in1, in2, sel);
	output [7:0] out;
	input [7:0] in1, in2;
	input sel;
	genvar j;
	generate for (j = 0 ; j < 8; j = j + 1) begin: mux_loop
	MUX2To1 m1(out[j], in1[j], in2[j], sel);
	end
	endgenerate
endmodule

module Fetch_Data(Data,P,Q);
	output [7:0] Data;
	output P;
	input [3:0] Q;
	wire [7:0] in1, in2;
	wire p1, p2;
	
	MEM1 m1 ({in1, p1}, Q[2:0]);
	MEM2 m2 ({in2, p2}, Q[2:0]);
	
	MUX16to8 mux1(Data, in1, in2, Q[3]);
	MUX2To1 mux2(P, p1, p2, Q[3]);
endmodule

module Parity_Checker(Data, P,  out);
	output out;
	input [7:0] Data;
	input P;
	wire dparity;
	
	assign dparity = Data[0] ^ Data[1] ^ Data[2] ^ Data[3] ^ Data[4] ^ Data[5] ^ Data[6] ^ Data[7];
	assign out = (dparity == P);
endmodule
	
	
module Design(out, clk, clear);
	output out;
	input clk, clear;
	wire [3:0] Q;
	wire [7:0] Data;
	wire P;
	
	Ripple_Counter r1 (Q, clk, clear);
	Fetch_Data  f1 (Data,P,Q);
	Parity_Checker p1 (Data, P , out);
	
endmodule
	
module TestBench;
	reg clk, clear;
	wire out;
	
	Design d1 (out, clk, clear);
	
	always 
	#1 clk = ~clk;
	
	initial 
	$monitor ($time, " clk = %b, clear = %b, out = %b ", clk, clear, out);
	initial begin
	$dumpfile("file.vcd");
	$dumpvars;
	clk = 1'b1; clear = 1'b1;
	#5 clear = 1'b0;
	#100 $finish;
	end
endmodule

test_20-21/file.vcd
$date
	Sun Nov 08 16:03:45 2020
$end
$version
	Icarus Verilog
$end
$timescale
	1s
$end
$scope module TestBench $end
$var wire 1 ! out $end
$var reg 1 " clear $end
$var reg 1 # clk $end
$scope module d1 $end
$var wire 1 " clear $end
$var wire 1 # clk $end
$var wire 1 ! out $end
$var wire 4 $ Q [3:0] $end
$var wire 1 % P $end
$var wire 8 & Data [7:0] $end
$scope module f1 $end
$var wire 1 ' p2 $end
$var wire 1 ( p1 $end
$var wire 8 ) in2 [7:0] $end
$var wire 8 * in1 [7:0] $end
$var wire 4 + Q [3:0] $end
$var wire 1 % P $end
$var wire 8 , Data [7:0] $end
$scope module m1 $end
$var wire 3 - Addr [2:0] $end
$var reg 9 . out [8:0] $end
$upscope $end
$scope module m2 $end
$var wire 3 / Addr [2:0] $end
$var reg 9 0 out [8:0] $end
$upscope $end
$scope module mux1 $end
$var wire 8 1 in1 [7:0] $end
$var wire 8 2 in2 [7:0] $end
$var wire 1 3 sel $end
$var wire 8 4 out [7:0] $end
$scope begin mux_loop[0] $end
$scope module m1 $end
$var wire 1 5 in1 $end
$var wire 1 6 in2 $end
$var wire 1 3 sel $end
$var wire 1 7 out $end
$upscope $end
$upscope $end
$scope begin mux_loop[1] $end
$scope module m1 $end
$var wire 1 8 in1 $end
$var wire 1 9 in2 $end
$var wire 1 3 sel $end
$var wire 1 : out $end
$upscope $end
$upscope $end
$scope begin mux_loop[2] $end
$scope module m1 $end
$var wire 1 ; in1 $end
$var wire 1 < in2 $end
$var wire 1 3 sel $end
$var wire 1 = out $end
$upscope $end
$upscope $end
$scope begin mux_loop[3] $end
$scope module m1 $end
$var wire 1 > in1 $end
$var wire 1 ? in2 $end
$var wire 1 3 sel $end
$var wire 1 @ out $end
$upscope $end
$upscope $end
$scope begin mux_loop[4] $end
$scope module m1 $end
$var wire 1 A in1 $end
$var wire 1 B in2 $end
$var wire 1 3 sel $end
$var wire 1 C out $end
$upscope $end
$upscope $end
$scope begin mux_loop[5] $end
$scope module m1 $end
$var wire 1 D in1 $end
$var wire 1 E in2 $end
$var wire 1 3 sel $end
$var wire 1 F out $end
$upscope $end
$upscope $end
$scope begin mux_loop[6] $end
$scope module m1 $end
$var wire 1 G in1 $end
$var wire 1 H in2 $end
$var wire 1 3 sel $end
$var wire 1 I out $end
$upscope $end
$upscope $end
$scope begin mux_loop[7] $end
$scope module m1 $end
$var wire 1 J in1 $end
$var wire 1 K in2 $end
$var wire 1 3 sel $end
$var wire 1 L out $end
$upscope $end
$upscope $end
$upscope $end
$scope module mux2 $end
$var wire 1 ( in1 $end
$var wire 1 ' in2 $end
$var wire 1 M sel $end
$var wire 1 % out $end
$upscope $end
$upscope $end
$scope module p1 $end
$var wire 8 N Data [7:0] $end
$var wire 1 % P $end
$var wire 1 O dparity $end
$var wire 1 ! out $end
$upscope $end
$scope module r1 $end
$var wire 1 " clear $end
$var wire 1 # clk $end
$var wire 1 P q3 $end
$var wire 1 Q q2 $end
$var wire 1 R q1 $end
$var wire 1 S q0 $end
$var wire 4 T Q [3:0] $end
$scope module d1 $end
$var wire 1 U Dnot $end
$var wire 1 " clear $end
$var wire 1 # clk $end
$var wire 1 S Qbar $end
$var wire 1 V Q $end
$var wire 1 S D $end
$scope module r1 $end
$var wire 1 U R $end
$var wire 1 S S $end
$var wire 1 " clear $end
$var wire 1 # clk $end
$var reg 1 V Q $end
$var reg 1 S Qbar $end
$upscope $end
$upscope $end
$scope module d2 $end
$var wire 1 W Dnot $end
$var wire 1 " clear $end
$var wire 1 S clk $end
$var wire 1 R Qbar $end
$var wire 1 X Q $end
$var wire 1 R D $end
$scope module r1 $end
$var wire 1 W R $end
$var wire 1 R S $end
$var wire 1 " clear $end
$var wire 1 S clk $end
$var reg 1 X Q $end
$var reg 1 R Qbar $end
$upscope $end
$upscope $end
$scope module d3 $end
$var wire 1 Y Dnot $end
$var wire 1 " clear $end
$var wire 1 R clk $end
$var wire 1 Q Qbar $end
$var wire 1 Z Q $end
$var wire 1 Q D $end
$scope module r1 $end
$var wire 1 Y R $end
$var wire 1 Q S $end
$var wire 1 " clear $end
$var wire 1 R clk $end
$var reg 1 Z Q $end
$var reg 1 Q Qbar $end
$upscope $end
$upscope $end
$scope module d4 $end
$var wire 1 [ Dnot $end
$var wire 1 " clear $end
$var wire 1 Q clk $end
$var wire 1 P Qbar $end
$var wire 1 \ Q $end
$var wire 1 P D $end
$scope module r1 $end
$var wire 1 [ R $end
$var wire 1 P S $end
$var wire 1 " clear $end
$var wire 1 Q clk $end
$var reg 1 \ Q $end
$var reg 1 P Qbar $end
$upscope $end
$upscope $end
$upscope $end
$upscope $end
$upscope $end
$enddefinitions $end
#0
$dumpvars
0\
0[
0Z
0Y
0X
0W
0V
0U
b0 T
1S
1R
1Q
1P
1O
b11111 N
0M
0L
0K
0J
0I
0H
0G
0F
0E
0D
1C
0B
1A
1@
0?
1>
1=
0<
1;
1:
09
18
17
06
15
b11111 4
03
b0 2
b11111 1
b0 0
b0 /
b111111 .
b0 -
b11111 ,
b0 +
b11111 *
b0 )
1(
0'
b11111 &
1%
b0 $
1#
1"
1!
$end
#1
0#
#2
1#
#3
0#
#4
1#
#5
0#
0"
#6
1!
1O
0:
0=
0@
b110001 &
b110001 ,
b110001 4
b110001 N
1F
19
1E
08
0;
0>
1D
b100010 )
b100010 2
b110001 *
b110001 1
b1000100 0
b1100011 .
1U
b1 /
b1 -
0S
b1 $
b1 +
b1 T
1V
1#
#7
0#
#8
1I
1<
1H
1G
1W
0R
1X
0!
0O
1:
0=
0@
b1010011 &
b1010011 ,
b1010011 4
b1010011 N
0F
09
0E
18
0;
0>
0D
b1000100 )
b1000100 2
b1010011 *
b1010011 1
b10001000 0
b10100111 .
0U
b10 /
b10 -
1S
b10 $
b10 +
b10 T
0V
1#
#9
0#
#10
1!
1O
0:
1=
b1110101 &
b1110101 ,
b1110101 4
b1110101 N
1F
19
1E
08
1;
1D
b1100110 )
b1100110 2
b1110101 *
b1110101 1
b11001100 0
b11101011 .
1U
b11 /
b11 -
0S
b11 $
b11 +
b11 T
1V
1#
#11
0#
#12
1?
1Y
0Q
1Z
0@
0I
0<
0H
0>
0G
0W
1R
0X
0!
0O
1:
1=
b10111 &
b10111 ,
b10111 4
b10111 N
0F
09
0E
18
1;
0D
b1000 )
b1000 2
b10111 *
b10111 1
b10000 0
b101111 .
0U
b100 /
b100 -
1S
b100 $
b100 +
b100 T
0V
1#
#13
0#
#14
0!
0O
0:
0=
1@
b111001 &
b111001 ,
b111001 4
b111001 N
1F
19
1E
08
0;
1>
1D
b101010 )
b101010 2
b111001 *
b111001 1
b1010100 0
b1110011 .
1U
b101 /
b101 -
0S
b101 $
b101 +
b101 T
1V
1#
#15
0#
#16
1I
1<
1H
1G
1W
0R
1X
1!
1O
1:
0=
1@
b1011011 &
b1011011 ,
b1011011 4
b1011011 N
0F
09
0E
18
0;
1>
0D
b1001100 )
b1001100 2
b1011011 *
b1011011 1
b10011000 0
b10110111 .
0U
b110 /
b110 -
1S
b110 $
b110 +
b110 T
0V
1#
#17
0#
#18
0!
0O
0:
1=
b1111101 &
b1111101 ,
b1111101 4
b1111101 N
1F
19
1E
08
1;
1D
b1101110 )
b1101110 2
b1111101 *
b1111101 1
b11011100 0
b11111011 .
1U
b111 /
b111 -
0S
b111 $
b111 +
b111 T
1V
1#
#19
0#
#20
0%
07
0C
1[
1M
13
0P
1\
0?
0Y
1Q
0Z
0@
0I
0<
0H
1>
0G
0W
1R
0X
1!
0O
0:
0=
b0 &
b0 ,
b0 4
b0 N
0F
09
0E
18
1;
0D
b0 )
b0 2
b11111 *
b11111 1
b0 0
b111111 .
0U
b0 /
b0 -
1S
b1000 $
b1000 +
b1000 T
0V
1#
#21
0#
#22
1!
0O
1:
b100010 &
b100010 ,
b100010 4
b100010 N
1F
19
1E
08
0;
0>
1D
b100010 )
b100010 2
b110001 *
b110001 1
b1000100 0
b1100011 .
1U
b1 /
b1 -
0S
b1001 $
b1001 +
b1001 T
1V
1#
#23
0#
#24
1=
1I
1<
1H
1G
1W
0R
1X
1!
0O
0:
b1000100 &
b1000100 ,
b1000100 4
b1000100 N
0F
09
0E
18
0;
0>
0D
b1000100 )
b1000100 2
b1010011 *
b1010011 1
b10001000 0
b10100111 .
0U
b10 /
b10 -
1S
b1010 $
b1010 +
b1010 T
0V
1#
#25
0#
#26
1!
0O
1:
b1100110 &
b1100110 ,
b1100110 4
b1100110 N
1F
19
1E
08
1;
1D
b1100110 )
b1100110 2
b1110101 *
b1110101 1
b11001100 0
b11101011 .
1U
b11 /
b11 -
0S
b1011 $
b1011 +
b1011 T
1V
1#
#27
0#
#28
1@
1?
1Y
0Q
1Z
0=
0I
0<
0H
0>
0G
0W
1R
0X
0!
1O
0:
b1000 &
b1000 ,
b1000 4
b1000 N
0F
09
0E
18
1;
0D
b1000 )
b1000 2
b10111 *
b10111 1
b10000 0
b101111 .
0U
b100 /
b100 -
1S
b1100 $
b1100 +
b1100 T
0V
1#
#29
0#
#30
0!
1O
1:
b101010 &
b101010 ,
b101010 4
b101010 N
1F
19
1E
08
0;
1>
1D
b101010 )
b101010 2
b111001 *
b111001 1
b1010100 0
b1110011 .
1U
b101 /
b101 -
0S
b1101 $
b1101 +
b1101 T
1V
1#
#31
0#
#32
1=
1I
1<
1H
1G
1W
0R
1X
0!
1O
0:
b1001100 &
b1001100 ,
b1001100 4
b1001100 N
0F
09
0E
18
0;
1>
0D
b1001100 )
b1001100 2
b1011011 *
b1011011 1
b10011000 0
b10110111 .
0U
b110 /
b110 -
1S
b1110 $
b1110 +
b1110 T
0V
1#
#33
0#
#34
0!
1O
1:
b1101110 &
b1101110 ,
b1101110 4
b1101110 N
1F
19
1E
08
1;
1D
b1101110 )
b1101110 2
b1111101 *
b1111101 1
b11011100 0
b11111011 .
1U
b111 /
b111 -
0S
b1111 $
b1111 +
b1111 T
1V
1#
#35
0#
#36
1%
17
1C
0[
0M
03
1P
0\
1@
0?
0Y
1Q
0Z
1=
0I
0<
0H
1>
0G
0W
1R
0X
1!
1O
1:
b11111 &
b11111 ,
b11111 4
b11111 N
0F
09
0E
18
1;
0D
b0 )
b0 2
b11111 *
b11111 1
b0 0
b111111 .
0U
b0 /
b0 -
1S
b0 $
b0 +
b0 T
0V
1#
#37
0#
#38
1!
1O
0:
0=
0@
b110001 &
b110001 ,
b110001 4
b110001 N
1F
19
1E
08
0;
0>
1D
b100010 )
b100010 2
b110001 *
b110001 1
b1000100 0
b1100011 .
1U
b1 /
b1 -
0S
b1 $
b1 +
b1 T
1V
1#
#39
0#
#40
1I
1<
1H
1G
1W
0R
1X
0!
0O
1:
0=
0@
b1010011 &
b1010011 ,
b1010011 4
b1010011 N
0F
09
0E
18
0;
0>
0D
b1000100 )
b1000100 2
b1010011 *
b1010011 1
b10001000 0
b10100111 .
0U
b10 /
b10 -
1S
b10 $
b10 +
b10 T
0V
1#
#41
0#
#42
1!
1O
0:
1=
b1110101 &
b1110101 ,
b1110101 4
b1110101 N
1F
19
1E
08
1;
1D
b1100110 )
b1100110 2
b1110101 *
b1110101 1
b11001100 0
b11101011 .
1U
b11 /
b11 -
0S
b11 $
b11 +
b11 T
1V
1#
#43
0#
#44
1?
1Y
0Q
1Z
0@
0I
0<
0H
0>
0G
0W
1R
0X
0!
0O
1:
1=
b10111 &
b10111 ,
b10111 4
b10111 N
0F
09
0E
18
1;
0D
b1000 )
b1000 2
b10111 *
b10111 1
b10000 0
b101111 .
0U
b100 /
b100 -
1S
b100 $
b100 +
b100 T
0V
1#
#45
0#
#46
0!
0O
0:
0=
1@
b111001 &
b111001 ,
b111001 4
b111001 N
1F
19
1E
08
0;
1>
1D
b101010 )
b101010 2
b111001 *
b111001 1
b1010100 0
b1110011 .
1U
b101 /
b101 -
0S
b101 $
b101 +
b101 T
1V
1#
#47
0#
#48
1I
1<
1H
1G
1W
0R
1X
1!
1O
1:
0=
1@
b1011011 &
b1011011 ,
b1011011 4
b1011011 N
0F
09
0E
18
0;
1>
0D
b1001100 )
b1001100 2
b1011011 *
b1011011 1
b10011000 0
b10110111 .
0U
b110 /
b110 -
1S
b110 $
b110 +
b110 T
0V
1#
#49
0#
#50
0!
0O
0:
1=
b1111101 &
b1111101 ,
b1111101 4
b1111101 N
1F
19
1E
08
1;
1D
b1101110 )
b1101110 2
b1111101 *
b1111101 1
b11011100 0
b11111011 .
1U
b111 /
b111 -
0S
b111 $
b111 +
b111 T
1V
1#
#51
0#
#52
0%
07
0C
1[
1M
13
0P
1\
0?
0Y
1Q
0Z
0@
0I
0<
0H
1>
0G
0W
1R
0X
1!
0O
0:
0=
b0 &
b0 ,
b0 4
b0 N
0F
09
0E
18
1;
0D
b0 )
b0 2
b11111 *
b11111 1
b0 0
b111111 .
0U
b0 /
b0 -
1S
b1000 $
b1000 +
b1000 T
0V
1#
#53
0#
#54
1!
0O
1:
b100010 &
b100010 ,
b100010 4
b100010 N
1F
19
1E
08
0;
0>
1D
b100010 )
b100010 2
b110001 *
b110001 1
b1000100 0
b1100011 .
1U
b1 /
b1 -
0S
b1001 $
b1001 +
b1001 T
1V
1#
#55
0#
#56
1=
1I
1<
1H
1G
1W
0R
1X
1!
0O
0:
b1000100 &
b1000100 ,
b1000100 4
b1000100 N
0F
09
0E
18
0;
0>
0D
b1000100 )
b1000100 2
b1010011 *
b1010011 1
b10001000 0
b10100111 .
0U
b10 /
b10 -
1S
b1010 $
b1010 +
b1010 T
0V
1#
#57
0#
#58
1!
0O
1:
b1100110 &
b1100110 ,
b1100110 4
b1100110 N
1F
19
1E
08
1;
1D
b1100110 )
b1100110 2
b1110101 *
b1110101 1
b11001100 0
b11101011 .
1U
b11 /
b11 -
0S
b1011 $
b1011 +
b1011 T
1V
1#
#59
0#
#60
1@
1?
1Y
0Q
1Z
0=
0I
0<
0H
0>
0G
0W
1R
0X
0!
1O
0:
b1000 &
b1000 ,
b1000 4
b1000 N
0F
09
0E
18
1;
0D
b1000 )
b1000 2
b10111 *
b10111 1
b10000 0
b101111 .
0U
b100 /
b100 -
1S
b1100 $
b1100 +
b1100 T
0V
1#
#61
0#
#62
0!
1O
1:
b101010 &
b101010 ,
b101010 4
b101010 N
1F
19
1E
08
0;
1>
1D
b101010 )
b101010 2
b111001 *
b111001 1
b1010100 0
b1110011 .
1U
b101 /
b101 -
0S
b1101 $
b1101 +
b1101 T
1V
1#
#63
0#
#64
1=
1I
1<
1H
1G
1W
0R
1X
0!
1O
0:
b1001100 &
b1001100 ,
b1001100 4
b1001100 N
0F
09
0E
18
0;
1>
0D
b1001100 )
b1001100 2
b1011011 *
b1011011 1
b10011000 0
b10110111 .
0U
b110 /
b110 -
1S
b1110 $
b1110 +
b1110 T
0V
1#
#65
0#
#66
0!
1O
1:
b1101110 &
b1101110 ,
b1101110 4
b1101110 N
1F
19
1E
08
1;
1D
b1101110 )
b1101110 2
b1111101 *
b1111101 1
b11011100 0
b11111011 .
1U
b111 /
b111 -
0S
b1111 $
b1111 +
b1111 T
1V
1#
#67
0#
#68
1%
17
1C
0[
0M
03
1P
0\
1@
0?
0Y
1Q
0Z
1=
0I
0<
0H
1>
0G
0W
1R
0X
1!
1O
1:
b11111 &
b11111 ,
b11111 4
b11111 N
0F
09
0E
18
1;
0D
b0 )
b0 2
b11111 *
b11111 1
b0 0
b111111 .
0U
b0 /
b0 -
1S
b0 $
b0 +
b0 T
0V
1#
#69
0#
#70
1!
1O
0:
0=
0@
b110001 &
b110001 ,
b110001 4
b110001 N
1F
19
1E
08
0;
0>
1D
b100010 )
b100010 2
b110001 *
b110001 1
b1000100 0
b1100011 .
1U
b1 /
b1 -
0S
b1 $
b1 +
b1 T
1V
1#
#71
0#
#72
1I
1<
1H
1G
1W
0R
1X
0!
0O
1:
0=
0@
b1010011 &
b1010011 ,
b1010011 4
b1010011 N
0F
09
0E
18
0;
0>
0D
b1000100 )
b1000100 2
b1010011 *
b1010011 1
b10001000 0
b10100111 .
0U
b10 /
b10 -
1S
b10 $
b10 +
b10 T
0V
1#
#73
0#
#74
1!
1O
0:
1=
b1110101 &
b1110101 ,
b1110101 4
b1110101 N
1F
19
1E
08
1;
1D
b1100110 )
b1100110 2
b1110101 *
b1110101 1
b11001100 0
b11101011 .
1U
b11 /
b11 -
0S
b11 $
b11 +
b11 T
1V
1#
#75
0#
#76
1?
1Y
0Q
1Z
0@
0I
0<
0H
0>
0G
0W
1R
0X
0!
0O
1:
1=
b10111 &
b10111 ,
b10111 4
b10111 N
0F
09
0E
18
1;
0D
b1000 )
b1000 2
b10111 *
b10111 1
b10000 0
b101111 .
0U
b100 /
b100 -
1S
b100 $
b100 +
b100 T
0V
1#
#77
0#
#78
0!
0O
0:
0=
1@
b111001 &
b111001 ,
b111001 4
b111001 N
1F
19
1E
08
0;
1>
1D
b101010 )
b101010 2
b111001 *
b111001 1
b1010100 0
b1110011 .
1U
b101 /
b101 -
0S
b101 $
b101 +
b101 T
1V
1#
#79
0#
#80
1I
1<
1H
1G
1W
0R
1X
1!
1O
1:
0=
1@
b1011011 &
b1011011 ,
b1011011 4
b1011011 N
0F
09
0E
18
0;
1>
0D
b1001100 )
b1001100 2
b1011011 *
b1011011 1
b10011000 0
b10110111 .
0U
b110 /
b110 -
1S
b110 $
b110 +
b110 T
0V
1#
#81
0#
#82
0!
0O
0:
1=
b1111101 &
b1111101 ,
b1111101 4
b1111101 N
1F
19
1E
08
1;
1D
b1101110 )
b1101110 2
b1111101 *
b1111101 1
b11011100 0
b11111011 .
1U
b111 /
b111 -
0S
b111 $
b111 +
b111 T
1V
1#
#83
0#
#84
0%
07
0C
1[
1M
13
0P
1\
0?
0Y
1Q
0Z
0@
0I
0<
0H
1>
0G
0W
1R
0X
1!
0O
0:
0=
b0 &
b0 ,
b0 4
b0 N
0F
09
0E
18
1;
0D
b0 )
b0 2
b11111 *
b11111 1
b0 0
b111111 .
0U
b0 /
b0 -
1S
b1000 $
b1000 +
b1000 T
0V
1#
#85
0#
#86
1!
0O
1:
b100010 &
b100010 ,
b100010 4
b100010 N
1F
19
1E
08
0;
0>
1D
b100010 )
b100010 2
b110001 *
b110001 1
b1000100 0
b1100011 .
1U
b1 /
b1 -
0S
b1001 $
b1001 +
b1001 T
1V
1#
#87
0#
#88
1=
1I
1<
1H
1G
1W
0R
1X
1!
0O
0:
b1000100 &
b1000100 ,
b1000100 4
b1000100 N
0F
09
0E
18
0;
0>
0D
b1000100 )
b1000100 2
b1010011 *
b1010011 1
b10001000 0
b10100111 .
0U
b10 /
b10 -
1S
b1010 $
b1010 +
b1010 T
0V
1#
#89
0#
#90
1!
0O
1:
b1100110 &
b1100110 ,
b1100110 4
b1100110 N
1F
19
1E
08
1;
1D
b1100110 )
b1100110 2
b1110101 *
b1110101 1
b11001100 0
b11101011 .
1U
b11 /
b11 -
0S
b1011 $
b1011 +
b1011 T
1V
1#
#91
0#
#92
1@
1?
1Y
0Q
1Z
0=
0I
0<
0H
0>
0G
0W
1R
0X
0!
1O
0:
b1000 &
b1000 ,
b1000 4
b1000 N
0F
09
0E
18
1;
0D
b1000 )
b1000 2
b10111 *
b10111 1
b10000 0
b101111 .
0U
b100 /
b100 -
1S
b1100 $
b1100 +
b1100 T
0V
1#
#93
0#
#94
0!
1O
1:
b101010 &
b101010 ,
b101010 4
b101010 N
1F
19
1E
08
0;
1>
1D
b101010 )
b101010 2
b111001 *
b111001 1
b1010100 0
b1110011 .
1U
b101 /
b101 -
0S
b1101 $
b1101 +
b1101 T
1V
1#
#95
0#
#96
1=
1I
1<
1H
1G
1W
0R
1X
0!
1O
0:
b1001100 &
b1001100 ,
b1001100 4
b1001100 N
0F
09
0E
18
0;
1>
0D
b1001100 )
b1001100 2
b1011011 *
b1011011 1
b10011000 0
b10110111 .
0U
b110 /
b110 -
1S
b1110 $
b1110 +
b1110 T
0V
1#
#97
0#
#98
0!
1O
1:
b1101110 &
b1101110 ,
b1101110 4
b1101110 N
1F
19
1E
08
1;
1D
b1101110 )
b1101110 2
b1111101 *
b1111101 1
b11011100 0
b11111011 .
1U
b111 /
b111 -
0S
b1111 $
b1111 +
b1111 T
1V
1#
#99
0#
#100
1%
17
1C
0[
0M
03
1P
0\
1@
0?
0Y
1Q
0Z
1=
0I
0<
0H
1>
0G
0W
1R
0X
1!
1O
1:
b11111 &
b11111 ,
b11111 4
b11111 N
0F
09
0E
18
1;
0D
b0 )
b0 2
b11111 *
b11111 1
b0 0
b111111 .
0U
b0 /
b0 -
1S
b0 $
b0 +
b0 T
0V
1#
#101
0#
#102
1!
1O
0:
0=
0@
b110001 &
b110001 ,
b110001 4
b110001 N
1F
19
1E
08
0;
0>
1D
b100010 )
b100010 2
b110001 *
b110001 1
b1000100 0
b1100011 .
1U
b1 /
b1 -
0S
b1 $
b1 +
b1 T
1V
1#
#103
0#
#104
1I
1<
1H
1G
1W
0R
1X
0!
0O
1:
0=
0@
b1010011 &
b1010011 ,
b1010011 4
b1010011 N
0F
09
0E
18
0;
0>
0D
b1000100 )
b1000100 2
b1010011 *
b1010011 1
b10001000 0
b10100111 .
0U
b10 /
b10 -
1S
b10 $
b10 +
b10 T
0V
1#
