Lab1/tb_bcdtogrey.v
`include "bcdtogrey.v"

module testbench;
	reg [0:3] in;
	wire [0:3] out;
	
	bcdtogrey_df g(in, out);
	initial
		begin
			$dumpfile("tb_bcdtogrey.vcd");
			$dumpvars;
			$monitor(, $time," in=%b | out=%b ", in, out);
			in = 4'b0000;
			#3 in = 4'b0001;
			#3 in = 4'b0010;
			#3 in = 4'b0011;
			#3 in = 4'b0100;
			#3 in = 4'b0101;
			#3 in = 4'b0110;
			#3 in = 4'b0111;
			#3 in = 4'b1000;
			#3 in = 4'b1001;
			#6 $finish;
		end
	
endmodule

Lab1/bcdtogrey.v
module bcdtogrey_gate (in , out);
	input [0:3] in;
	output [0:3] out;
	
	buf b(out[0], in[0]);
	xor x1( out[1], in[0], in[1]);
	xor x2(out[2], in[1], in[2]);
	xor x3 (out[3], in[2], in[3]);
endmodule


module bcdtogrey_df(in , out);
	output [0:3] out;
	input [0:3] in;
	assign out[0] = in[0];
	assign out[1] = in[0] ^ in[1];
	assign out[2] = in[1] ^ in[2];
	assign out[3] = in[2] ^ in[3];
	
endmodule

Lab1/tb_bcdtogrey.vcd
$date
	Thu Sep 17 15:43:05 2020
$end
$version
	Icarus Verilog
$end
$timescale
	1s
$end
$scope module bcdtogrey_gate $end
$var wire 4 ! in [0:3] $end
$var wire 4 " out [0:3] $end
$upscope $end
$scope module testbench $end
$var wire 4 # out [0:3] $end
$var reg 4 $ in [0:3] $end
$scope module g $end
$var wire 4 % in [0:3] $end
$var wire 4 & out [0:3] $end
$upscope $end
$upscope $end
$enddefinitions $end
#0
$dumpvars
b0 &
b0 %
b0 $
b0 #
bzxxx "
bz !
$end
#3
b1 #
b1 &
b1 $
b1 %
#6
b11 #
b11 &
b10 $
b10 %
#9
b10 #
b10 &
b11 $
b11 %
#12
b110 #
b110 &
b100 $
b100 %
#15
b111 #
b111 &
b101 $
b101 %
#18
b101 #
b101 &
b110 $
b110 %
#21
b100 #
b100 &
b111 $
b111 %
#24
b1100 #
b1100 &
b1000 $
b1000 %
#27
b1101 #
b1101 &
b1001 $
b1001 %
