Lab3/block_nonblock.v
module nonblocking(in, clk, out);
	input in, clk;
	output out;
	reg q1, q2, out;
	
	always@ (posedge clk)
	begin
	q1 <= in;
	q2 <= q1;
	out <= q2;
	end 
endmodule

module blocking(in, clk, out);
	input in, clk;
	output out;
	reg q1, q2, out;
	
	always@ (posedge clk)
	begin
	q1 = in;
	q2 = q1;
	out = q2;
	end
endmodule

module testbench;
	reg in, clk;
	wire out;
	blocking n(in, clk, out);
	
	always @(posedge clk) begin
	$display ("in=%b, clk=%b, out=%b\n" ,in, clk, out);
	end
	
	initial begin
	forever begin
	clk = 0;
	#5 
	clk = 1;
	#5 clk = 0;
	end
	end
	
	initial begin
	$dumpfile("block_nonblock.vcd");
	$dumpvars(0, testbench);
	in = 1;
	#10
	in = 0;
	#50 
	in = 1;
	#50
	in = 0;
	end 
endmodule

Lab3/block_nonblock.vcd
$date
	Thu Oct 01 14:52:52 2020
$end
$version
	Icarus Verilog
$end
$timescale
	1s
$end
$scope module testbench $end
$var wire 1 ! out $end
$var reg 1 " clk $end
$var reg 1 # in $end
$scope module n $end
$var wire 1 " clk $end
$var wire 1 # in $end
$var reg 1 ! out $end
$var reg 1 $ q1 $end
$var reg 1 % q2 $end
$upscope $end
$upscope $end
$enddefinitions $end
#0
$dumpvars
x%
x$
1#
0"
x!
$end
#5
1!
1%
1$
1"
#10
0"
0#
#15
0!
0%
0$
1"
#20
0"
#25
1"
#30
0"
#35
1"
#40
0"
#45
1"
#50
0"
#55
1"
#60
0"
1#
#65
1!
1%
1$
1"
#70
0"
#75
1"
#80
0"
#85
1"
#90
0"
#95
1"
#100
0"
#105
1"
#110
0"
0#
#115
0!
0%
0$
1"
