Lab3/mealy.v
module mealy(clk, rst, inp, outp);
	input clk, rst, inp;
	output outp;
	reg [0:1] state;
	reg outp;
	
	always@(posedge clk, posedge rst) begin
	if (rst) begin
	state <= 2'b00;
	outp <= 0;
	end
	
	else begin
	case(state)
	
		2'b00:begin
			if(inp)begin
			state <= 2'b01;
			outp <= 0;
			end
			else begin
			state <= 2'b10;
			outp <= 0;
			end
			end
			
		2'b01:begin
			if(inp) begin
			state <= 2'b00;
			outp <= 1;
			end
			else begin
			state <= 2'b10;
			outp <= 0;
			end
			end
			
		2'b10: begin
			if(inp) begin
			state <= 2'b01;
			outp <= 0;
			end
			else begin
			state <= 2'b00;
			outp <= 1;
			end
		end
		
		default: begin
			state <= 2'b00;
			outp <= 0;
		end
	endcase
	
	end
	end
endmodule

//Test bench

module mealy_test;
	reg clk, rst, inp;
	wire outp;
	reg [15:0] seq;
	integer i;
	
	mealy duty(clk, rst, inp, outp);
	
	initial
	begin
	$dumpfile("mealy.vcd");
	$dumpvars(0, mealy_test);
	clk = 0;
	rst = 1;
	seq = 16'b0101_0111_0111_0010;
	#5 rst = 0;
	
	for(i = 0; i <= 15; i = i + 1)
	begin
	inp = seq[i];
	#2 clk = 1;
	#2 clk = 0;
	$display(" Input = ", inp, ", Output = ", outp, " State = ", duty.state);
	end
	testing;
	end
	
	task testing;
	for(i = 0; i <= 15; i = i + 1)
	begin
	inp = $random % 2;
	#2 clk = 1;
	#2 clk = 0;
	$display (" Input = ", inp, ", Output = ", outp, " State = ", duty.state);
	end
	endtask
endmodule

Lab3/mealy.vcd
$date
	Thu Oct 01 15:47:30 2020
$end
$version
	Icarus Verilog
$end
$timescale
	1s
$end
$scope module mealy_test $end
$var wire 1 ! outp $end
$var reg 1 " clk $end
$var reg 1 # inp $end
$var reg 1 $ rst $end
$var reg 16 % seq [15:0] $end
$var integer 32 & i [31:0] $end
$scope module duty $end
$var wire 1 " clk $end
$var wire 1 # inp $end
$var wire 1 $ rst $end
$var reg 1 ! outp $end
$var reg 2 ' state [0:1] $end
$upscope $end
$scope task testing $end
$upscope $end
$upscope $end
$enddefinitions $end
#0
$dumpvars
b0 '
bx &
b101011101110010 %
1$
x#
0"
0!
$end
#5
0#
b0 &
0$
#7
b10 '
1"
#9
1#
b1 &
0"
#11
b1 '
1"
#13
0#
b10 &
0"
#15
b10 '
1"
#17
b11 &
0"
#19
1!
b0 '
1"
#21
1#
b100 &
0"
#23
0!
b1 '
1"
#25
b101 &
0"
#27
1!
b0 '
1"
#29
b110 &
0"
#31
0!
b1 '
1"
#33
0#
b111 &
0"
#35
b10 '
1"
#37
1#
b1000 &
0"
#39
b1 '
1"
#41
b1001 &
0"
#43
1!
b0 '
1"
#45
b1010 &
0"
#47
0!
b1 '
1"
#49
0#
b1011 &
0"
#51
b10 '
1"
#53
1#
b1100 &
0"
#55
b1 '
1"
#57
0#
b1101 &
0"
#59
b10 '
1"
#61
1#
b1110 &
0"
#63
b1 '
1"
#65
0#
b1111 &
0"
#67
b10 '
1"
#69
b0 &
0"
#71
1!
b0 '
1"
#73
1#
b1 &
0"
#75
0!
b1 '
1"
#77
b10 &
0"
#79
1!
b0 '
1"
#81
b11 &
0"
#83
0!
b1 '
1"
#85
b100 &
0"
#87
1!
b0 '
1"
#89
b101 &
0"
#91
0!
b1 '
1"
#93
b110 &
0"
#95
1!
b0 '
1"
#97
0#
b111 &
0"
#99
0!
b10 '
1"
#101
1#
b1000 &
0"
#103
b1 '
1"
#105
b1001 &
0"
#107
1!
b0 '
1"
#109
0#
b1010 &
0"
#111
0!
b10 '
1"
#113
1#
b1011 &
0"
#115
b1 '
1"
#117
b1100 &
0"
#119
1!
b0 '
1"
#121
0#
b1101 &
0"
#123
0!
b10 '
1"
#125
1#
b1110 &
0"
#127
b1 '
1"
#129
0#
b1111 &
0"
#131
b10 '
1"
#133
b10000 &
0"
